flaspi/__init__.py
flaspi/call_test.py
flaspi/test.py
flaspi-0.1.0.dist-info/METADATA
flaspi-0.1.0.dist-info/WHEEL
flaspi-0.1.0.dist-info/top_level.txt
flaspi-0.1.0.dist-info/RECORD
